{"namedChunkGroups":{"polyfill":{"name":"polyfill","assets":[{"name":"webpack-runtime-f55309c5bbd9c7231e02.js","size":3800},{"name":"polyfill-80cf8b9874c05ad8eda9.js","size":82499}],"filteredAssets":0,"assetsSize":86299,"filteredAuxiliaryAssets":2,"auxiliaryAssetsSize":216504},"app":{"name":"app","assets":[{"name":"webpack-runtime-f55309c5bbd9c7231e02.js","size":3800},{"name":"framework-058ab522f55c127e61bb.js","size":128967},{"name":"styles.562047a5fc830f1334b8.css","size":806},{"name":"app-fbf1ecdcbdee0daae3ad.js","size":74879}],"filteredAssets":0,"assetsSize":208452,"filteredAuxiliaryAssets":3,"auxiliaryAssetsSize":663011},"component---src-pages-404-js":{"name":"component---src-pages-404-js","assets":[{"name":"component---src-pages-404-js-cab782bbf0ece0e88d43.js","size":818}],"filteredAssets":0,"assetsSize":818,"filteredAuxiliaryAssets":1,"auxiliaryAssetsSize":1902},"component---src-pages-index-js":{"name":"component---src-pages-index-js","assets":[{"name":"component---src-pages-index-js-f698a14995bf1a251833.js","size":3498}],"filteredAssets":0,"assetsSize":3498,"filteredAuxiliaryAssets":1,"auxiliaryAssetsSize":3943}},"assetsByChunkName":{"polyfill":["webpack-runtime-f55309c5bbd9c7231e02.js","polyfill-80cf8b9874c05ad8eda9.js"],"app":["webpack-runtime-f55309c5bbd9c7231e02.js","framework-058ab522f55c127e61bb.js","styles.562047a5fc830f1334b8.css","app-fbf1ecdcbdee0daae3ad.js"],"component---src-pages-404-js":["component---src-pages-404-js-cab782bbf0ece0e88d43.js"],"component---src-pages-index-js":["component---src-pages-index-js-f698a14995bf1a251833.js"]},"childAssetsByChunkName":{}}